etlkit/__init__.py
etlkit/extract.py
etlkit/load.py
etlkit/pipeline.py
etlkit/transform.py
etlkit-0.1.0.dist-info/licenses/LICENSE
etlkit-0.1.0.dist-info/METADATA
etlkit-0.1.0.dist-info/WHEEL
etlkit-0.1.0.dist-info/top_level.txt
etlkit-0.1.0.dist-info/RECORD
