Metadata-Version: 2.4
Name: etlkit
Version: 0.1.0
Summary: A simple etl pipeline package for CSV, API, and DB sources
Author-email: Dorin Jerotich <jerotichdorin@gmail.com>
License: MIT License
Requires-Python: >=3.8
License-File: LICENSE
Requires-Dist: pandas
Requires-Dist: requests
Requires-Dist: psycopg2-binary
Requires-Dist: openpyxl
Dynamic: license-file
